credPass/__init__.py
credPass-1.1.dist-info/METADATA
credPass-1.1.dist-info/RECORD
credPass-1.1.dist-info/WHEEL
credPass-1.1.dist-info/top_level.txt
