Metadata-Version: 2.1
Name: credPass
Version: 1.1
Summary: python class to load credentials or other sensitive data
Home-page: https://github.com/FedericoOlivieri/networkAutomation/
Author: Federico Olivieri
Author-email: lvrfrc87@gmail.com
License: MIT
Platform: UNKNOWN
